<config>
    <!-- Log with a warning message that mod is loaded (warning simply shows mod path cant be removed because that path doesnt exist) -->
    <remove xpath="/JankMod_Loaded[@modname='NRZ_7JankTweaks'][@filename='\Config\recipes.xml']" />

    <!-- Remove guns from workbench so perfect qualiy weapons cant be crafted (or any quality for that mater)-->
    <remove xpath="/recipes/recipe[@name='gun44Magnum']" />
    <remove xpath="/recipes/recipe[@name='gunAK47']" />
    <remove xpath="/recipes/recipe[@name='gunBlunderbuss']" />
    <remove xpath="/recipes/recipe[@name='gunCompoundBow']" />
    <remove xpath="/recipes/recipe[@name='gunHuntingRifle']" />
    <remove xpath="/recipes/recipe[@name='gunMR10']" />
    <remove xpath="/recipes/recipe[@name='gunPistol']" />
    <remove xpath="/recipes/recipe[@name='gunPumpShotgun']" />
    <remove xpath="/recipes/recipe[@name='gunRocketLauncher']" />
    <remove xpath="/recipes/recipe[@name='gunSMG5']" />
    <remove xpath="/recipes/recipe[@name='gunToolNailgun']" />
    <!-- <remove xpath="/recipes/recipe[@name='gunCrossbow']" /> -->

    <!-- Remove military clothes from workbench so perfect quality clothes cant be crafted -->
    <remove xpath="/recipes/recipe[@name='armorMilitaryBoots']" />
    <remove xpath="/recipes/recipe[@name='armorMilitaryGloves']" />
    <remove xpath="/recipes/recipe[@name='armorMilitaryHelmet']" />
    <remove xpath="/recipes/recipe[@name='armorMilitaryLegs']" />
    <remove xpath="/recipes/recipe[@name='armorMilitaryVest']" />
    
    <!-- Remove Tools from workbench so perfect quality tools cant be crafted -->
    <remove xpath="/recipes/recipe[@name='meleeToolAuger']" />
    <remove xpath="/recipes/recipe[@name='meleeToolChainsaw']" />
    <remove xpath="/recipes/recipe[@name='meleeToolClawHammer']" />
    <remove xpath="/recipes/recipe[@name='meleeToolFireaxeIron']" />
    <remove xpath="/recipes/recipe[@name='meleeToolFireaxeSteel']" />
    <remove xpath="/recipes/recipe[@name='meleeToolHoeIron']" />
    <remove xpath="/recipes/recipe[@name='meleeToolHuntingKnife']" />
    <remove xpath="/recipes/recipe[@name='meleeToolMachete']" />
    <remove xpath="/recipes/recipe[@name='meleeToolPickaxeIron']" />
    <remove xpath="/recipes/recipe[@name='meleeToolPickaxeSteel']" />
    <remove xpath="/recipes/recipe[@name='meleeToolShovelIron']" />
    <remove xpath="/recipes/recipe[@name='meleeToolShovelSteel']" />
    <remove xpath="/recipes/recipe[@name='meleeToolSledgehammer']" />
    <remove xpath="/recipes/recipe[@name='meleeToolWrench']" />

    <!-- Add brass to required resource to craft storage chest -->
    <append xpath="/recipes/recipe[@name='cntSecureStorageChest']">
	    <ingredient name="resourceScrapBrass" count="2"/>
    </append>

    <!-- Add brass to required resource to craft secureDoorWooden -->
    <append xpath="/recipes/recipe[@name='secureDoorWooden']">
	    <ingredient name="resourceScrapBrass" count="2"/>
    </append>

    <!-- Add brass to required resource to craft secureDoorWooden -->
    <append xpath="/recipes/recipe[@name='secureDoorWooden']">
	    <ingredient name="resourceScrapBrass" count="2"/>
    </append>

    <append xpath="/recipes">
        <recipe name="houseFrontDoor1_v1" count="1" craft_area="tablesaw">
        	<ingredient name="resourceWood" count="10"/>
        	<ingredient name="resourceDoorKnob" count="1"/>
            <ingredient name="resourceScrapBrass" count="3"/>
        </recipe>
    </append>

    <append xpath="/recipes">
        <recipe name="houseFrontDoor2_v1" count="1" craft_area="tablesaw">
        	<ingredient name="resourceWood" count="10"/>
        	<ingredient name="resourceDoorKnob" count="1"/>
            <ingredient name="resourceScrapBrass" count="3"/>
        </recipe>
    </append>

    <!-- Adjust meat value in recipes (Who decided you need 5 meat to make 1 cooked meat ?) -->
    <!-- <set xpath="/recipes/recipe[@name='meleeToolAuger']/ingredient[@name='foodRawMeat']/@count">1</set> -->
    <set xpath="/recipes/recipe[contains(@name, 'food')]/ingredient[@name='foodRawMeat']/@count">1</set>

    <!-- Remove gascan recipe - the gas issue should be fixed in a18 so no need to mess with this
    <remove xpath="/recipes/recipe[@name='ammoGasCan']" />
   
    <recipe name="ammoGasCan" count="100" craft_area="chemistryStation" tags="learnable">
	    <ingredient name="resourceOilShale" count="12"/>
    </recipe>

    <recipe name="ammoGasCan" count="600" craft_exp_gain="0" craft_time="5" always_unlocked="true">
	    <ingredient name="oilBarrel" count="1"/>
    </recipe>
    -->
</config>